TLSynDataGene/Generator.py
TLSynDataGene/__init__.py
TLSynDataGene-0.0.1.dist-info/LICENSE
TLSynDataGene-0.0.1.dist-info/METADATA
TLSynDataGene-0.0.1.dist-info/WHEEL
TLSynDataGene-0.0.1.dist-info/top_level.txt
TLSynDataGene-0.0.1.dist-info/RECORD
